winram/__init__.py
winram/constants.py
winram/py.typed
winram/virtual.py
winram/_raw/__init__.py
winram/_raw/bindings.py
winram/_raw/dll.py
winram-1.5.dist-info/licenses/LICENSE.txt
winram-1.5.dist-info/METADATA
winram-1.5.dist-info/WHEEL
winram-1.5.dist-info/top_level.txt
winram-1.5.dist-info/RECORD
