Metadata-Version: 2.4
Name: WinRAM
Version: 1.5
Summary: Exposes Windows bindings to the memory interface.
Author-email: WCG847 <heelmods@gmail.com>
License-Expression: GPL-3.0-or-later
Keywords: WINDOWS,WIN32,WINNT,MEMORY,VIRTUALALLOC
Classifier: Development Status :: 5 - Production/Stable
Classifier: Programming Language :: Python :: Free Threading :: 4 - Resilient
Classifier: Intended Audience :: Developers
Classifier: Topic :: System
Classifier: Operating System :: Microsoft :: Windows :: Windows 11
Classifier: Typing :: Typed
Classifier: Programming Language :: Python :: 3.14
Requires-Python: >=3.14
License-File: LICENSE.txt
Dynamic: license-file
